ee_fourier_transform/__init__.py
ee_fourier_transform/common.py
ee_fourier_transform/ee_fourier_transform.py
ee_fourier_transform-0.0.1.dist-info/LICENSE
ee_fourier_transform-0.0.1.dist-info/METADATA
ee_fourier_transform-0.0.1.dist-info/WHEEL
ee_fourier_transform-0.0.1.dist-info/entry_points.txt
ee_fourier_transform-0.0.1.dist-info/top_level.txt
ee_fourier_transform-0.0.1.dist-info/RECORD
