Metadata-Version: 2.1
Name: ee_fourier_transform
Version: 0.0.1
Summary: Package for doing time series modeling
Author-email: Ryan Hamilton <ryangilberthamilton@gmail.com>
License: MIT License
Project-URL: Homepage, https://github.com/Hamilton97/ee_fourier_transform
Keywords: ee_fourier_transform
Classifier: Intended Audience :: Developers
Classifier: License :: OSI Approved :: MIT License
Classifier: Natural Language :: English
Classifier: Programming Language :: Python :: 3.8
Classifier: Programming Language :: Python :: 3.9
Classifier: Programming Language :: Python :: 3.10
Classifier: Programming Language :: Python :: 3.11
Classifier: Programming Language :: Python :: 3.12
Requires-Python: >=3.8
License-File: LICENSE
Requires-Dist: numpy
Provides-Extra: all
Requires-Dist: ee-fourier-transform[extra] ; extra == 'all'
Provides-Extra: extra
Requires-Dist: pandas ; extra == 'extra'
